bankedpy/__init__.py
bankedpy/common.py
bankedpy/payment_session/__init__.py
bankedpy/payment_session/schemas.py
bankedpy-0.1.4.dist-info/WHEEL
bankedpy-0.1.4.dist-info/METADATA
bankedpy-0.1.4.dist-info/RECORD
